[
    {
        "genres": [
            "Shooter",
            "Racing",
            "Adventure"
        ],
        "name": "Grand Theft Auto V",
        "url": "\/\/images.igdb.com\/igdb\/image\/upload\/t_thumb\/co2lbd.jpg"
    },
    {
        "genres": [
            "Role-playing (RPG)",
            "Adventure"
        ],
        "name": "The Witcher 3: Wild Hunt",
        "url": "\/\/images.igdb.com\/igdb\/image\/upload\/t_thumb\/co1wyy.jpg"
    },
    {
        "genres": [
            "Shooter",
            "Platform",
            "Puzzle",
            "Adventure"
        ],
        "name": "Portal 2",
        "url": "\/\/images.igdb.com\/igdb\/image\/upload\/t_thumb\/co1rs4.jpg"
    },
    {
        "genres": [
            "Role-playing (RPG)",
            "Adventure"
        ],
        "name": "The Elder Scrolls V: Skyrim",
        "url": "\/\/images.igdb.com\/igdb\/image\/upload\/t_thumb\/co1tnw.jpg"
    },
    {
        "genres": [
            "Shooter",
            "Platform",
            "Puzzle"
        ],
        "name": "Portal",
        "url": "\/\/images.igdb.com\/igdb\/image\/upload\/t_thumb\/co1x7d.jpg"
    },
    {
        "genres": [
            "Shooter",
            "Racing",
            "Adventure"
        ],
        "name": "Grand Theft Auto: San Andreas",
        "url": "\/\/images.igdb.com\/igdb\/image\/upload\/t_thumb\/co2lb9.jpg"
    },
    {
        "genres": [
            "Shooter",
            "Adventure"
        ],
        "name": "The Last of Us",
        "url": "\/\/images.igdb.com\/igdb\/image\/upload\/t_thumb\/co1r7f.jpg"
    },
    {
        "genres": [
            "Shooter"
        ],
        "name": "Half-Life 2",
        "url": "\/\/images.igdb.com\/igdb\/image\/upload\/t_thumb\/co1nmw.jpg"
    },
    {
        "genres": [
            "Shooter",
            "Puzzle",
            "Role-playing (RPG)",
            "Adventure"
        ],
        "name": "BioShock",
        "url": "\/\/images.igdb.com\/igdb\/image\/upload\/t_thumb\/co2mli.jpg"
    },
    {
        "genres": [
            "Platform",
            "Adventure"
        ],
        "name": "Assassin's Creed II",
        "url": "\/\/images.igdb.com\/igdb\/image\/upload\/t_thumb\/co1rcf.jpg"
    },
    {
        "genres": [
            "Role-playing (RPG)",
            "Hack and slash\/Beat 'em up",
            "Adventure"
        ],
        "name": "God of War",
        "url": "\/\/images.igdb.com\/igdb\/image\/upload\/t_thumb\/co1tmu.jpg"
    },
    {
        "genres": [
            "Shooter",
            "Racing",
            "Adventure",
            "Arcade"
        ],
        "name": "Grand Theft Auto: Vice City",
        "url": "\/\/images.igdb.com\/igdb\/image\/upload\/t_thumb\/co2lbb.jpg"
    },
    {
        "genres": [
            "Shooter",
            "Role-playing (RPG)",
            "Adventure"
        ],
        "name": "Mass Effect 2",
        "url": "\/\/images.igdb.com\/igdb\/image\/upload\/t_thumb\/co20ac.jpg"
    },
    {
        "genres": [
            "Shooter",
            "Adventure"
        ],
        "name": "BioShock Infinite",
        "url": "\/\/images.igdb.com\/igdb\/image\/upload\/t_thumb\/co2n12.jpg"
    },
    {
        "genres": [
            "Shooter",
            "Puzzle",
            "Adventure"
        ],
        "name": "Half-Life",
        "url": "\/\/images.igdb.com\/igdb\/image\/upload\/t_thumb\/co7q89.jpg"
    },
    {
        "genres": [
            "Shooter",
            "Role-playing (RPG)",
            "Adventure"
        ],
        "name": "Red Dead Redemption 2",
        "url": "\/\/images.igdb.com\/igdb\/image\/upload\/t_thumb\/co1q1f.jpg"
    },
    {
        "genres": [
            "Hack and slash\/Beat 'em up",
            "Adventure"
        ],
        "name": "Batman: Arkham Asylum",
        "url": "\/\/images.igdb.com\/igdb\/image\/upload\/t_thumb\/co1voj.jpg"
    },
    {
        "genres": [
            "Puzzle",
            "Role-playing (RPG)",
            "Adventure"
        ],
        "name": "The Legend of Zelda: Breath of the Wild",
        "url": "\/\/images.igdb.com\/igdb\/image\/upload\/t_thumb\/co3p2d.jpg"
    },
    {
        "genres": [
            "Hack and slash\/Beat 'em up",
            "Adventure"
        ],
        "name": "Batman: Arkham City",
        "url": "\/\/images.igdb.com\/igdb\/image\/upload\/t_thumb\/co1voh.jpg"
    },
    {
        "genres": [
            "Shooter",
            "Role-playing (RPG)"
        ],
        "name": "Mass Effect",
        "url": "\/\/images.igdb.com\/igdb\/image\/upload\/t_thumb\/co1x7o.jpg"
    },
    {
        "genres": [
            "Shooter",
            "Adventure"
        ],
        "name": "Uncharted 4: A Thief's End",
        "url": "\/\/images.igdb.com\/igdb\/image\/upload\/t_thumb\/co1r7h.jpg"
    },
    {
        "genres": [
            "Shooter",
            "Platform",
            "Puzzle",
            "Adventure"
        ],
        "name": "Tomb Raider",
        "url": "\/\/images.igdb.com\/igdb\/image\/upload\/t_thumb\/co1rbu.jpg"
    },
    {
        "genres": [
            "Shooter",
            "Role-playing (RPG)",
            "Adventure"
        ],
        "name": "Red Dead Redemption",
        "url": "\/\/images.igdb.com\/igdb\/image\/upload\/t_thumb\/co2lcv.jpg"
    },
    {
        "genres": [
            "Shooter",
            "Role-playing (RPG)",
            "Adventure"
        ],
        "name": "Horizon Zero Dawn",
        "url": "\/\/images.igdb.com\/igdb\/image\/upload\/t_thumb\/co2una.jpg"
    },
    {
        "genres": [
            "Shooter",
            "Platform",
            "Adventure"
        ],
        "name": "Uncharted 2: Among Thieves",
        "url": "\/\/images.igdb.com\/igdb\/image\/upload\/t_thumb\/co1tnb.jpg"
    },
    {
        "genres": [
            "Shooter",
            "Adventure"
        ],
        "name": "Far Cry 3",
        "url": "\/\/images.igdb.com\/igdb\/image\/upload\/t_thumb\/co1vpd.jpg"
    },
    {
        "genres": [
            "Shooter",
            "Role-playing (RPG)"
        ],
        "name": "Fallout: New Vegas",
        "url": "\/\/images.igdb.com\/igdb\/image\/upload\/t_thumb\/co1u60.jpg"
    },
    {
        "genres": [
            "Simulator",
            "Adventure"
        ],
        "name": "Minecraft",
        "url": "\/\/images.igdb.com\/igdb\/image\/upload\/t_thumb\/co49x5.jpg"
    },
    {
        "genres": [
            "Role-playing (RPG)",
            "Adventure"
        ],
        "name": "The Legend of Zelda: Ocarina of Time",
        "url": "\/\/images.igdb.com\/igdb\/image\/upload\/t_thumb\/co3nnx.jpg"
    },
    {
        "genres": [
            "Shooter",
            "Role-playing (RPG)",
            "Adventure"
        ],
        "name": "Mass Effect 3",
        "url": "\/\/images.igdb.com\/igdb\/image\/upload\/t_thumb\/co1x7q.jpg"
    },
    {
        "genres": [
            "Shooter",
            "Role-playing (RPG)"
        ],
        "name": "Borderlands 2",
        "url": "\/\/images.igdb.com\/igdb\/image\/upload\/t_thumb\/co20tn.jpg"
    },
    {
        "genres": [
            "Platform",
            "Adventure"
        ],
        "name": "Super Mario 64",
        "url": "\/\/images.igdb.com\/igdb\/image\/upload\/t_thumb\/co721v.jpg"
    },
    {
        "genres": [
            "Shooter",
            "Puzzle"
        ],
        "name": "Doom",
        "url": "\/\/images.igdb.com\/igdb\/image\/upload\/t_thumb\/co1nc7.jpg"
    },
    {
        "genres": [
            "Puzzle",
            "Role-playing (RPG)",
            "Adventure",
            "Indie"
        ],
        "name": "Life is Strange",
        "url": "\/\/images.igdb.com\/igdb\/image\/upload\/t_thumb\/co1r8e.jpg"
    },
    {
        "genres": [
            "Platform",
            "Adventure"
        ],
        "name": "Super Mario World",
        "url": "\/\/images.igdb.com\/igdb\/image\/upload\/t_thumb\/co65za.jpg"
    },
    {
        "genres": [
            "Shooter",
            "Simulator"
        ],
        "name": "Call of Duty 4: Modern Warfare",
        "url": "\/\/images.igdb.com\/igdb\/image\/upload\/t_thumb\/co1wko.jpg"
    },
    {
        "genres": [
            "Platform",
            "Adventure"
        ],
        "name": "Assassin's Creed",
        "url": "\/\/images.igdb.com\/igdb\/image\/upload\/t_thumb\/co1rrw.jpg"
    },
    {
        "genres": [
            "Puzzle",
            "Role-playing (RPG)",
            "Adventure"
        ],
        "name": "Dishonored",
        "url": "\/\/images.igdb.com\/igdb\/image\/upload\/t_thumb\/co5pcs.jpg"
    },
    {
        "genres": [
            "Shooter",
            "Racing",
            "Adventure"
        ],
        "name": "Grand Theft Auto IV",
        "url": "\/\/images.igdb.com\/igdb\/image\/upload\/t_thumb\/co2lbv.jpg"
    },
    {
        "genres": [
            "Shooter"
        ],
        "name": "Max Payne",
        "url": "\/\/images.igdb.com\/igdb\/image\/upload\/t_thumb\/co3wb2.jpg"
    },
    {
        "genres": [
            "Point-and-click",
            "Adventure"
        ],
        "name": "The Walking Dead",
        "url": "\/\/images.igdb.com\/igdb\/image\/upload\/t_thumb\/co2j1g.jpg"
    },
    {
        "genres": [
            "Puzzle",
            "Adventure"
        ],
        "name": "Assassin's Creed Brotherhood",
        "url": "\/\/images.igdb.com\/igdb\/image\/upload\/t_thumb\/co6t4d.jpg"
    },
    {
        "genres": [
            "Shooter",
            "Role-playing (RPG)"
        ],
        "name": "Fallout 3",
        "url": "\/\/images.igdb.com\/igdb\/image\/upload\/t_thumb\/co1ycw.jpg"
    },
    {
        "genres": [
            "Platform",
            "Adventure"
        ],
        "name": "Assassin's Creed IV Black Flag",
        "url": "\/\/images.igdb.com\/igdb\/image\/upload\/t_thumb\/co4qfn.jpg"
    },
    {
        "genres": [
            "Hack and slash\/Beat 'em up",
            "Adventure"
        ],
        "name": "Marvel's Spider-Man",
        "url": "\/\/images.igdb.com\/igdb\/image\/upload\/t_thumb\/co1r77.jpg"
    },
    {
        "genres": [
            "Role-playing (RPG)",
            "Turn-based strategy (TBS)",
            "Adventure",
            "Indie"
        ],
        "name": "Undertale",
        "url": "\/\/images.igdb.com\/igdb\/image\/upload\/t_thumb\/co2855.jpg"
    },
    {
        "genres": [
            "Role-playing (RPG)"
        ],
        "name": "Dragon Age: Origins",
        "url": "\/\/images.igdb.com\/igdb\/image\/upload\/t_thumb\/co2mvs.jpg"
    },
    {
        "genres": [
            "Platform",
            "Adventure"
        ],
        "name": "Super Mario Odyssey",
        "url": "\/\/images.igdb.com\/igdb\/image\/upload\/t_thumb\/co1mxf.jpg"
    },
    {
        "genres": [
            "Role-playing (RPG)",
            "Adventure"
        ],
        "name": "Bloodborne",
        "url": "\/\/images.igdb.com\/igdb\/image\/upload\/t_thumb\/co1rba.jpg"
    },
    {
        "genres": [
            "Platform",
            "Adventure",
            "Indie"
        ],
        "name": "Hollow Knight",
        "url": "\/\/images.igdb.com\/igdb\/image\/upload\/t_thumb\/co1rgi.jpg"
    },
    {
        "genres": [
            "Shooter",
            "Role-playing (RPG)"
        ],
        "name": "Fallout 4",
        "url": "\/\/images.igdb.com\/igdb\/image\/upload\/t_thumb\/co1yc6.jpg"
    },
    {
        "genres": [
            "Shooter",
            "Adventure"
        ],
        "name": "The Last of Us Remastered",
        "url": "\/\/images.igdb.com\/igdb\/image\/upload\/t_thumb\/co5zks.jpg"
    },
    {
        "genres": [
            "Role-playing (RPG)",
            "Adventure"
        ],
        "name": "Dark Souls III",
        "url": "\/\/images.igdb.com\/igdb\/image\/upload\/t_thumb\/co1vcf.jpg"
    },
    {
        "genres": [
            "Platform",
            "Puzzle",
            "Adventure",
            "Indie"
        ],
        "name": "Inside",
        "url": "\/\/images.igdb.com\/igdb\/image\/upload\/t_thumb\/co2fca.jpg"
    },
    {
        "genres": [
            "Platform"
        ],
        "name": "Super Mario Bros. 3",
        "url": "\/\/images.igdb.com\/igdb\/image\/upload\/t_thumb\/co7ozx.jpg"
    },
    {
        "genres": [
            "Puzzle",
            "Adventure"
        ],
        "name": "The Legend of Zelda: A Link to the Past",
        "url": "\/\/images.igdb.com\/igdb\/image\/upload\/t_thumb\/co3vzn.jpg"
    },
    {
        "genres": [
            "Tactical",
            "Adventure"
        ],
        "name": "Metal Gear Solid",
        "url": "\/\/images.igdb.com\/igdb\/image\/upload\/t_thumb\/co7k2q.jpg"
    },
    {
        "genres": [
            "Role-playing (RPG)",
            "Adventure"
        ],
        "name": "The Elder Scrolls IV: Oblivion",
        "url": "\/\/images.igdb.com\/igdb\/image\/upload\/t_thumb\/co1tc8.jpg"
    },
    {
        "genres": [
            "Platform",
            "Puzzle",
            "Adventure",
            "Indie"
        ],
        "name": "Limbo",
        "url": "\/\/images.igdb.com\/igdb\/image\/upload\/t_thumb\/co1qrs.jpg"
    },
    {
        "genres": [
            "Shooter",
            "Adventure"
        ],
        "name": "Resident Evil 4",
        "url": "\/\/images.igdb.com\/igdb\/image\/upload\/t_thumb\/co2wk8.jpg"
    },
    {
        "genres": [
            "Shooter",
            "Racing",
            "Simulator",
            "Adventure"
        ],
        "name": "Grand Theft Auto III",
        "url": "\/\/images.igdb.com\/igdb\/image\/upload\/t_thumb\/co2lb8.jpg"
    },
    {
        "genres": [
            "Role-playing (RPG)",
            "Turn-based strategy (TBS)",
            "Adventure"
        ],
        "name": "Final Fantasy VII",
        "url": "\/\/images.igdb.com\/igdb\/image\/upload\/t_thumb\/co2kx2.jpg"
    },
    {
        "genres": [
            "Shooter",
            "Platform",
            "Adventure"
        ],
        "name": "Uncharted 3: Drake's Deception",
        "url": "\/\/images.igdb.com\/igdb\/image\/upload\/t_thumb\/co1tp8.jpg"
    },
    {
        "genres": [
            "Real Time Strategy (RTS)",
            "Strategy"
        ],
        "name": "Warcraft III: Reign of Chaos",
        "url": "\/\/images.igdb.com\/igdb\/image\/upload\/t_thumb\/co1xuq.jpg"
    },
    {
        "genres": [
            "Shooter",
            "Puzzle"
        ],
        "name": "Half-Life 2: Episode Two",
        "url": "\/\/images.igdb.com\/igdb\/image\/upload\/t_thumb\/co2mw2.jpg"
    },
    {
        "genres": [
            "Shooter"
        ],
        "name": "Call of Duty: Modern Warfare 2",
        "url": "\/\/images.igdb.com\/igdb\/image\/upload\/t_thumb\/co3cwt.jpg"
    },
    {
        "genres": [
            "Adventure"
        ],
        "name": "Assassin's Creed III",
        "url": "\/\/images.igdb.com\/igdb\/image\/upload\/t_thumb\/co1xii.jpg"
    },
    {
        "genres": [
            "Role-playing (RPG)",
            "Adventure"
        ],
        "name": "Dark Souls",
        "url": "\/\/images.igdb.com\/igdb\/image\/upload\/t_thumb\/co1x78.jpg"
    },
    {
        "genres": [
            "Hack and slash\/Beat 'em up",
            "Adventure"
        ],
        "name": "Batman: Arkham Knight",
        "url": "\/\/images.igdb.com\/igdb\/image\/upload\/t_thumb\/co1nh1.jpg"
    },
    {
        "genres": [
            "Role-playing (RPG)",
            "Hack and slash\/Beat 'em up"
        ],
        "name": "Diablo II",
        "url": "\/\/images.igdb.com\/igdb\/image\/upload\/t_thumb\/co3gfq.jpg"
    },
    {
        "genres": [
            "Role-playing (RPG)",
            "Adventure"
        ],
        "name": "The Witcher 2: Assassins of Kings",
        "url": "\/\/images.igdb.com\/igdb\/image\/upload\/t_thumb\/co1wy4.jpg"
    },
    {
        "genres": [
            "Platform",
            "Puzzle",
            "Adventure"
        ],
        "name": "Ori and the Blind Forest",
        "url": "\/\/images.igdb.com\/igdb\/image\/upload\/t_thumb\/co1y41.jpg"
    },
    {
        "genres": [
            "Role-playing (RPG)",
            "Simulator",
            "Strategy",
            "Indie"
        ],
        "name": "Stardew Valley",
        "url": "\/\/images.igdb.com\/igdb\/image\/upload\/t_thumb\/xrpmydnu9rpxvxfjkiu7.jpg"
    },
    {
        "genres": [
            "Role-playing (RPG)",
            "Adventure"
        ],
        "name": "Star Wars: Knights of the Old Republic",
        "url": "\/\/images.igdb.com\/igdb\/image\/upload\/t_thumb\/co1tmz.jpg"
    },
    {
        "genres": [
            "Role-playing (RPG)",
            "Hack and slash\/Beat 'em up",
            "Adventure"
        ],
        "name": "Middle-earth: Shadow of Mordor",
        "url": "\/\/images.igdb.com\/igdb\/image\/upload\/t_thumb\/co20pd.jpg"
    },
    {
        "genres": [
            "Role-playing (RPG)",
            "Hack and slash\/Beat 'em up"
        ],
        "name": "NieR: Automata",
        "url": "\/\/images.igdb.com\/igdb\/image\/upload\/t_thumb\/co5pcj.jpg"
    },
    {
        "genres": [
            "Fighting",
            "Shooter",
            "Racing",
            "Adventure"
        ],
        "name": "Mafia",
        "url": "\/\/images.igdb.com\/igdb\/image\/upload\/t_thumb\/co1qrt.jpg"
    },
    {
        "genres": [
            "Shooter",
            "Tactical"
        ],
        "name": "Counter-Strike: Global Offensive",
        "url": "\/\/images.igdb.com\/igdb\/image\/upload\/t_thumb\/co6996.jpg"
    },
    {
        "genres": [
            "Platform",
            "Adventure"
        ],
        "name": "Super Mario Bros.",
        "url": "\/\/images.igdb.com\/igdb\/image\/upload\/t_thumb\/co6pib.jpg"
    },
    {
        "genres": [
            "Shooter",
            "Adventure"
        ],
        "name": "Wolfenstein: The New Order",
        "url": "\/\/images.igdb.com\/igdb\/image\/upload\/t_thumb\/co21c0.jpg"
    },
    {
        "genres": [
            "Shooter",
            "Adventure"
        ],
        "name": "The Last of Us Part II",
        "url": "\/\/images.igdb.com\/igdb\/image\/upload\/t_thumb\/co5ziw.jpg"
    },
    {
        "genres": [
            "Shooter",
            "Adventure"
        ],
        "name": "Rise of the Tomb Raider",
        "url": "\/\/images.igdb.com\/igdb\/image\/upload\/t_thumb\/co1rqa.jpg"
    },
    {
        "genres": [
            "Shooter",
            "Indie",
            "Arcade"
        ],
        "name": "Hotline Miami",
        "url": "\/\/images.igdb.com\/igdb\/image\/upload\/t_thumb\/co1vqp.jpg"
    },
    {
        "genres": [
            "Role-playing (RPG)",
            "Adventure"
        ],
        "name": "Chrono Trigger",
        "url": "\/\/images.igdb.com\/igdb\/image\/upload\/t_thumb\/co3plw.jpg"
    },
    {
        "genres": [
            "Platform",
            "Puzzle",
            "Adventure"
        ],
        "name": "Shadow of the Colossus",
        "url": "\/\/images.igdb.com\/igdb\/image\/upload\/t_thumb\/co1ozz.jpg"
    },
    {
        "genres": [
            "Shooter"
        ],
        "name": "Call of Duty: Black Ops",
        "url": "\/\/images.igdb.com\/igdb\/image\/upload\/t_thumb\/co1wkl.jpg"
    },
    {
        "genres": [
            "Shooter",
            "Platform",
            "Adventure"
        ],
        "name": "Uncharted: Drake's Fortune",
        "url": "\/\/images.igdb.com\/igdb\/image\/upload\/t_thumb\/co1tp7.jpg"
    },
    {
        "genres": [
            "Role-playing (RPG)",
            "Strategy",
            "Adventure"
        ],
        "name": "South Park: The Stick of Truth",
        "url": "\/\/images.igdb.com\/igdb\/image\/upload\/t_thumb\/co1v8x.jpg"
    },
    {
        "genres": [
            "Shooter",
            "Strategy"
        ],
        "name": "Overwatch",
        "url": "\/\/images.igdb.com\/igdb\/image\/upload\/t_thumb\/co1rcb.jpg"
    },
    {
        "genres": [
            "Shooter",
            "Tactical",
            "Adventure"
        ],
        "name": "Metal Gear Solid 3: Snake Eater",
        "url": "\/\/images.igdb.com\/igdb\/image\/upload\/t_thumb\/co5ei5.jpg"
    },
    {
        "genres": [
            "Shooter",
            "Puzzle"
        ],
        "name": "Dead Space",
        "url": "\/\/images.igdb.com\/igdb\/image\/upload\/t_thumb\/co2g7w.jpg"
    },
    {
        "genres": [
            "Point-and-click",
            "Adventure"
        ],
        "name": "The Wolf Among Us",
        "url": "\/\/images.igdb.com\/igdb\/image\/upload\/t_thumb\/co1rcy.jpg"
    },
    {
        "genres": [
            "Adventure"
        ],
        "name": "Assassin's Creed Revelations",
        "url": "\/\/images.igdb.com\/igdb\/image\/upload\/t_thumb\/co1xih.jpg"
    },
    {
        "genres": [
            "Role-playing (RPG)",
            "Hack and slash\/Beat 'em up",
            "Adventure",
            "Indie"
        ],
        "name": "Hades",
        "url": "\/\/images.igdb.com\/igdb\/image\/upload\/t_thumb\/co39vc.jpg"
    },
    {
        "genres": [
            "Platform",
            "Adventure"
        ],
        "name": "Super Mario Galaxy",
        "url": "\/\/images.igdb.com\/igdb\/image\/upload\/t_thumb\/co21ro.jpg"
    },
    {
        "genres": [
            "Shooter",
            "Racing",
            "Adventure"
        ],
        "name": "Mafia II",
        "url": "\/\/images.igdb.com\/igdb\/image\/upload\/t_thumb\/co2n13.jpg"
    },
    {
        "genres": [
            "Platform",
            "Adventure",
            "Indie"
        ],
        "name": "Celeste",
        "url": "\/\/images.igdb.com\/igdb\/image\/upload\/t_thumb\/co3byy.jpg"
    },
    {
        "genres": [
            "Real Time Strategy (RTS)",
            "Strategy"
        ],
        "name": "StarCraft",
        "url": "\/\/images.igdb.com\/igdb\/image\/upload\/t_thumb\/co1x7n.jpg"
    },
    {
        "genres": [
            "Simulator",
            "Strategy",
            "Turn-based strategy (TBS)"
        ],
        "name": "Sid Meier's Civilization V",
        "url": "\/\/images.igdb.com\/igdb\/image\/upload\/t_thumb\/co20up.jpg"
    },
    {
        "genres": [
            "Platform",
            "Adventure"
        ],
        "name": "Journey",
        "url": "\/\/images.igdb.com\/igdb\/image\/upload\/t_thumb\/co1q8q.jpg"
    }
]